mlinnate/__init__.py
mlinnate/mlinnate.py
mlinnate-1.1.5.dist-info/LICENSE
mlinnate-1.1.5.dist-info/METADATA
mlinnate-1.1.5.dist-info/WHEEL
mlinnate-1.1.5.dist-info/top_level.txt
mlinnate-1.1.5.dist-info/RECORD
