Metadata-Version: 2.1
Name: mlinnate
Version: 1.1.5
Summary: Innate stands for Integrated Neural Network Automatic Trainer and Evaluator
Home-page: https://llrgit.in2p3.fr/online/innate
Author: Frederic Magniette
Author-email: magniette@llr.in2p3.fr
License: UNKNOWN
Platform: UNKNOWN
Classifier: Programming Language :: Python :: 3
Classifier: License :: OSI Approved :: MIT License
Classifier: Operating System :: OS Independent
Requires-Dist: tensorflow (>2)
Requires-Dist: keras
Requires-Dist: numpy (<1.19.0)
Requires-Dist: matplotlib
Requires-Dist: dill
Requires-Dist: rpyc
Requires-Dist: IPython
Requires-Dist: h5py
